{
	"format_version": "1.12.0",
	"minecraft:geometry": [
		{
			"description": {
				"identifier": "geometry.unknown",
				"texture_width": 128,
				"texture_height": 128,
				"visible_bounds_width": 4,
				"visible_bounds_height": 19,
				"visible_bounds_offset": [0, 1.5, 0]
			},
			"bones": [
				{
					"name": "bone2",
					"pivot": [0, 0, 0],
					"rotation": [0, 180, 0],
					"cubes": [
						{
							"origin": [6.6, 0, -3],
							"size": [6, 85, 6],
							"uv": {
								"north": {"uv": [6, 28.15858], "uv_size": [6, 84.84142]},
								"east": {"uv": [0, 28.15858], "uv_size": [6, 84.84142]},
								"south": {"uv": [18, 28.15858], "uv_size": [6, 84.84142]},
								"west": {"uv": [12, 28.15858], "uv_size": [6, 84.84142]},
								"up": {"uv": [6, 0], "uv_size": [6, 6]},
								"down": {"uv": [12, 6], "uv_size": [6, -6]}
							}
						},
						{"origin": [4.6, 0, -5], "size": [10, 2, 10], "uv": [68, 45]},
						{"origin": [5.6, 2, -4], "size": [8, 2, 8], "uv": [68, 82]},
						{"origin": [-0.4, -127.5, -2], "size": [1, 6.5, 1], "pivot": [0.7, -121, -1.5], "rotation": [0, 0, 17.5], "uv": [94, 64]},
						{"origin": [-0.4, -127.5, -2], "size": [1, 6.5, 1], "pivot": [0.7, -121, -1.5], "rotation": [0, 0, 17.5], "uv": [94, 71]},
						{"origin": [3.6, 8, 3], "size": [12, 19, 5], "uv": [60, 21]},
						{
							"origin": [7.6, 43, 3],
							"size": [4, 42, 1],
							"uv": {
								"north": {"uv": [25, 44.19596], "uv_size": [4, 41.80404]},
								"east": {"uv": [24, 44.19596], "uv_size": [1, 41.80404]},
								"south": {"uv": [30, 44.19596], "uv_size": [4, 41.80404]},
								"west": {"uv": [29, 44.19596], "uv_size": [1, 41.80404]},
								"up": {"uv": [25, 21], "uv_size": [4, 1]},
								"down": {"uv": [29, 22], "uv_size": [4, -1]}
							}
						},
						{"origin": [11.6, 43, 3], "size": [5, 1.3, 1], "uv": [90, 92]},
						{
							"origin": [15.6, 44, 3],
							"size": [1, 0.8, 1],
							"uv": {
								"north": {"uv": [22, 0], "uv_size": [1, 1]},
								"east": {"uv": [22, 1], "uv_size": [1, 1]},
								"south": {"uv": [22, 2], "uv_size": [1, 1]},
								"west": {"uv": [22, 3], "uv_size": [1, 1]},
								"up": {"uv": [22, 4], "uv_size": [1, 1]},
								"down": {"uv": [22, 6], "uv_size": [1, -1]}
							}
						},
						{"origin": [11.6, 49, 3], "size": [5, 1.3, 1], "uv": [94, 21]},
						{
							"origin": [15.6, 50, 3],
							"size": [1, 0.8, 1],
							"uv": {
								"north": {"uv": [21, 0], "uv_size": [1, 1]},
								"east": {"uv": [21, 1], "uv_size": [1, 1]},
								"south": {"uv": [21, 2], "uv_size": [1, 1]},
								"west": {"uv": [21, 3], "uv_size": [1, 1]},
								"up": {"uv": [21, 4], "uv_size": [1, 1]},
								"down": {"uv": [21, 6], "uv_size": [1, -1]}
							}
						},
						{"origin": [11.6, 55, 3], "size": [5, 1.3, 1], "uv": [94, 23]},
						{
							"origin": [15.6, 56, 3],
							"size": [1, 0.8, 1],
							"uv": {
								"north": {"uv": [20, 0], "uv_size": [1, 1]},
								"east": {"uv": [20, 1], "uv_size": [1, 1]},
								"south": {"uv": [20, 2], "uv_size": [1, 1]},
								"west": {"uv": [20, 3], "uv_size": [1, 1]},
								"up": {"uv": [20, 4], "uv_size": [1, 1]},
								"down": {"uv": [20, 6], "uv_size": [1, -1]}
							}
						},
						{"origin": [11.6, 61, 3], "size": [5, 1.3, 1], "uv": [94, 25]},
						{
							"origin": [15.6, 62, 3],
							"size": [1, 0.8, 1],
							"uv": {
								"north": {"uv": [19, 0], "uv_size": [1, 1]},
								"east": {"uv": [19, 1], "uv_size": [1, 1]},
								"south": {"uv": [19, 2], "uv_size": [1, 1]},
								"west": {"uv": [19, 3], "uv_size": [1, 1]},
								"up": {"uv": [19, 4], "uv_size": [1, 1]},
								"down": {"uv": [19, 6], "uv_size": [1, -1]}
							}
						},
						{"origin": [11.6, 67, 3], "size": [5, 1.3, 1], "uv": [94, 27]},
						{
							"origin": [15.6, 68, 3],
							"size": [1, 0.8, 1],
							"uv": {
								"north": {"uv": [18, 0], "uv_size": [1, 1]},
								"east": {"uv": [18, 1], "uv_size": [1, 1]},
								"south": {"uv": [18, 2], "uv_size": [1, 1]},
								"west": {"uv": [18, 3], "uv_size": [1, 1]},
								"up": {"uv": [18, 4], "uv_size": [1, 1]},
								"down": {"uv": [18, 6], "uv_size": [1, -1]}
							}
						},
						{"origin": [11.6, 73, 3], "size": [5, 1.3, 1], "uv": [94, 29]},
						{
							"origin": [15.6, 74, 3],
							"size": [1, 0.8, 1],
							"uv": {
								"north": {"uv": [5, 2], "uv_size": [1, 1]},
								"east": {"uv": [3, 5], "uv_size": [1, 1]},
								"south": {"uv": [5, 3], "uv_size": [1, 1]},
								"west": {"uv": [4, 5], "uv_size": [1, 1]},
								"up": {"uv": [5, 4], "uv_size": [1, 1]},
								"down": {"uv": [5, 6], "uv_size": [1, -1]}
							}
						},
						{"origin": [11.6, 79, 3], "size": [5, 1.3, 1], "uv": [94, 31]},
						{
							"origin": [15.6, 80, 3],
							"size": [1, 0.8, 1],
							"uv": {
								"north": {"uv": [4, 4], "uv_size": [1, 1]},
								"east": {"uv": [0, 5], "uv_size": [1, 1]},
								"south": {"uv": [5, 0], "uv_size": [1, 1]},
								"west": {"uv": [1, 5], "uv_size": [1, 1]},
								"up": {"uv": [5, 1], "uv_size": [1, 1]},
								"down": {"uv": [2, 6], "uv_size": [1, -1]}
							}
						},
						{
							"origin": [7.6, 39, -4],
							"size": [4, 46, 1],
							"uv": {
								"north": {"uv": [35, 38], "uv_size": [4, 46]},
								"east": {"uv": [34, 38], "uv_size": [1, 46]},
								"south": {"uv": [40, 38], "uv_size": [4, 46]},
								"west": {"uv": [39, 38], "uv_size": [1, 46]},
								"up": {"uv": [35, 21], "uv_size": [4, 1]},
								"down": {"uv": [39, 22], "uv_size": [4, -1]}
							}
						},
						{
							"origin": [7.6, 12, -4.5],
							"size": [4, 45, 0.5],
							"uv": {
								"north": {"uv": [44, 21], "uv_size": [8, 50]},
								"east": {"uv": [44, 21], "uv_size": [0, 50]},
								"south": {"uv": [52, 21], "uv_size": [8, 50]},
								"west": {"uv": [52, 21], "uv_size": [0, 50]},
								"up": {"uv": [44, 21], "uv_size": [8, 0]},
								"down": {"uv": [52, 21], "uv_size": [8, 0]}
							}
						}
					]
				},
				{
					"name": "bone",
					"pivot": [1, 103, -1],
					"rotation": [0, 180, 0],
					"cubes": [
						{"origin": [5.92584, 89.225, -12.4], "size": [13, 1.3, 20.8], "uv": [24, 0]},
						{"origin": [5.92584, 90.525, -12.4], "size": [1.3, 13, 1.3], "uv": [56, 71]},
						{"origin": [17.62584, 90.525, -12.4], "size": [1.3, 13, 1.3], "uv": [56, 85]},
						{"origin": [17.62584, 90.525, 7.1], "size": [1.3, 13, 1.3], "uv": [52, 86]},
						{"origin": [5.92584, 90.525, 7.1], "size": [1.3, 13, 1.3], "uv": [90, 64]},
						{"origin": [7.22584, 102.225, -12.4], "size": [10.4, 1.3, 1.3], "uv": [34, 84]},
						{"origin": [7.22584, 102.225, 7.1], "size": [10.4, 1.3, 1.3], "uv": [90, 13]},
						{"origin": [7.22584, 97.025, -12.4], "size": [10.4, 1.3, 1.3], "uv": [90, 15]},
						{"origin": [8.42584, 102.225, -3.3], "size": [18.3, 1.3, 1.3], "pivot": [17.62584, 90.525, -2], "rotation": [0, -90, 0], "uv": [90, 0]},
						{"origin": [8.42584, 97.025, -3.3], "size": [18.2, 1.3, 1.3], "pivot": [17.62584, 85.325, -2], "rotation": [0, -90, 0], "uv": [90, 2]},
						{"origin": [9.72584, 97.025, -2.3], "size": [5.2, 1.3, 1.3], "pivot": [5.92584, 85.325, -1], "rotation": [0, -90, 0], "uv": [44, 78]},
						{"origin": [9.72584, 102.225, -3], "size": [5.3, 1.3, 1.3], "pivot": [5.92584, 90.525, -1.7], "rotation": [0, -90, 0], "uv": [44, 80]},
						{"origin": [-0.57416, 85.325, -2.65], "size": [10.4, 2.6, 1.3], "uv": [90, 10]},
						{"origin": [5.92584, 85.325, -4.6], "size": [1.3, 2.6, 5.2], "uv": [44, 71]},
						{"origin": [0.72584, 85.325, -4.6], "size": [1.3, 2.6, 5.2], "uv": [90, 57]},
						{"origin": [-0.57416, 87.925, -4.6], "size": [9.1, 1.3, 5.2], "uv": [24, 86]},
						{"origin": [-0.57416, 89.225, -4.6], "size": [5.2, 1.3, 5.2], "uv": [90, 4]},
						{"origin": [0.72584, 90.525, -3.3], "size": [2.6, 51.5, 2.6], "uv": [60, 45]},
						{"origin": [-3.17416, 111.325, -4.6], "size": [10.4, 24.7, 1.3], "uv": [68, 57]},
						{"origin": [9.72584, 97.025, -16.2], "size": [5.2, 1.3, 1.3], "pivot": [5.92584, 85.325, -14.9], "rotation": [0, -90, 0], "uv": [44, 82]},
						{"origin": [9.72584, 102.225, -16.3], "size": [5.2, 1.3, 1.3], "pivot": [5.92584, 90.525, -15], "rotation": [0, -90, 0], "uv": [74, 92]},
						{"origin": [5.92584, 90.525, -7.2], "size": [1.3, 13, 1.3], "uv": [24, 92]},
						{"origin": [5.92584, 90.525, 1.9], "size": [1.3, 13, 1.3], "uv": [28, 92]},
						{"origin": [0.72584, 103.525, -4.6], "size": [2.6, 2.6, 1.3], "uv": [94, 41]},
						{"origin": [0.72584, 103.525, -4.6], "size": [1.3, 9.23, 1.3], "pivot": [2.12584, 103.525, -3.95], "rotation": [0, 0, -26], "uv": [46, 92]},
						{"origin": [2.02584, 103.525, -4.6], "size": [1.3, 9.23, 1.3], "pivot": [2.12584, 103.525, -3.95], "rotation": [0, 0, 26], "uv": [86, 92]},
						{"origin": [-3.1, 134.2, -7.6], "size": [4, 1, 3], "uv": [90, 17]},
						{"origin": [-3.1, 128, -7.6], "size": [4, 1, 3], "uv": [90, 78]},
						{"origin": [3, 128, -7.6], "size": [4, 1, 3], "uv": [32, 92]},
						{"origin": [-3.1, 115.6, -7.6], "size": [4, 1, 3], "uv": [60, 92]},
						{
							"origin": [8.6, 85, -5],
							"size": [6, 4.2, 6],
							"uv": {
								"north": {"uv": [6, 6], "uv_size": [6, 4.19216]},
								"east": {"uv": [0, 6], "uv_size": [6, 4.19216]},
								"south": {"uv": [18, 6], "uv_size": [6, 4.19216]},
								"west": {"uv": [12, 6], "uv_size": [6, 4.19216]},
								"up": {"uv": [6, 0], "uv_size": [6, 6]},
								"down": {"uv": [12, 6], "uv_size": [6, -6]}
							}
						},
						{
							"origin": [9.6, 85, 1],
							"size": [4, 4.3, 1],
							"uv": {
								"north": {"uv": [25, 22], "uv_size": [4, 4.27994]},
								"east": {"uv": [24, 22], "uv_size": [1, 4.27994]},
								"south": {"uv": [30, 22], "uv_size": [4, 4.27994]},
								"west": {"uv": [29, 22], "uv_size": [1, 4.27994]},
								"up": {"uv": [25, 21], "uv_size": [4, 1]},
								"down": {"uv": [29, 22], "uv_size": [4, -1]}
							}
						},
						{"origin": [13.6, 85, 1], "size": [5, 1.3, 1], "uv": [94, 39]},
						{
							"origin": [17.6, 86, 1],
							"size": [1, 0.8, 1],
							"uv": {
								"north": {"uv": [0, 0], "uv_size": [1, 1]},
								"east": {"uv": [0, 1], "uv_size": [1, 1]},
								"south": {"uv": [1, 0], "uv_size": [1, 1]},
								"west": {"uv": [1, 1], "uv_size": [1, 1]},
								"up": {"uv": [0, 2], "uv_size": [1, 1]},
								"down": {"uv": [2, 1], "uv_size": [1, -1]}
							}
						},
						{
							"origin": [9.6, 85, -6],
							"size": [4, 4, 1],
							"uv": {
								"north": {"uv": [35, 22], "uv_size": [4, 4]},
								"east": {"uv": [34, 22], "uv_size": [1, 4]},
								"south": {"uv": [40, 22], "uv_size": [4, 4]},
								"west": {"uv": [39, 22], "uv_size": [1, 4]},
								"up": {"uv": [35, 21], "uv_size": [4, 1]},
								"down": {"uv": [39, 22], "uv_size": [4, -1]}
							}
						}
					]
				}
			]
		}
	]
}